CREDITS.rst
LICENSE
MANIFEST.in
Makefile.in
README-standalone.rst
README.rst
configure
configure.ac
pyproject.toml
setup.py
docs/_build/html/__init__.py
images/__init__.py
images/snake-whiskey.jpg
mod_wsgi_standalone.egg-info/PKG-INFO
mod_wsgi_standalone.egg-info/SOURCES.txt
mod_wsgi_standalone.egg-info/dependency_links.txt
mod_wsgi_standalone.egg-info/entry_points.txt
mod_wsgi_standalone.egg-info/not-zip-safe
mod_wsgi_standalone.egg-info/requires.txt
mod_wsgi_standalone.egg-info/top_level.txt
src/__init__.py
src/server/__init__.py
src/server/environ.py
src/server/mod_wsgi.c
src/server/wsgi_apache.c
src/server/wsgi_apache.h
src/server/wsgi_buckets.c
src/server/wsgi_buckets.h
src/server/wsgi_convert.c
src/server/wsgi_convert.h
src/server/wsgi_daemon.c
src/server/wsgi_daemon.h
src/server/wsgi_interp.c
src/server/wsgi_interp.h
src/server/wsgi_logger.c
src/server/wsgi_logger.h
src/server/wsgi_memory.c
src/server/wsgi_memory.h
src/server/wsgi_metrics.c
src/server/wsgi_metrics.h
src/server/wsgi_python.h
src/server/wsgi_restrict.c
src/server/wsgi_restrict.h
src/server/wsgi_server.c
src/server/wsgi_server.h
src/server/wsgi_stream.c
src/server/wsgi_stream.h
src/server/wsgi_thread.c
src/server/wsgi_thread.h
src/server/wsgi_validate.c
src/server/wsgi_validate.h
src/server/wsgi_version.h
src/server/management/__init__.py
src/server/management/commands/__init__.py
src/server/management/commands/runmodwsgi.py
tests/access.wsgi
tests/auth.wsgi
tests/environ.wsgi
tests/events.wsgi
tests/hello.wsgi